jj_spec_validator/__init__.py
jj_spec_validator/_config.py
jj_spec_validator/validate_spec.py
jj_spec_validator/validator.py
jj_spec_validator/validator_base.py
jj_spec_validator/utils/__init__.py
jj_spec_validator/utils/_cacheir.py
jj_spec_validator/utils/_common.py
jj_spec_validator/utils/_refiner.py
jj_spec_validator/utils/_spec_matcher.py
jj_spec_validator-1.0.0.dist-info/METADATA
jj_spec_validator-1.0.0.dist-info/WHEEL
jj_spec_validator-1.0.0.dist-info/top_level.txt
jj_spec_validator-1.0.0.dist-info/RECORD
