Metadata-Version: 2.1
Name: jj-spec-validator
Version: 1.0.0
Summary: jj mocks validator for openapi specs
Home-page: https://github.com/Maestoz/jj-spec-validator
Author: Sam Roz
Author-email: rolez777@gmail.com
License: Apache-2.0
Classifier: License :: OSI Approved :: Apache Software License
Classifier: Programming Language :: Python :: 3.10
Classifier: Programming Language :: Python :: 3.11
Requires-Python: >=3.10
Requires-Dist: httpx<1.0.0,>=0.27.0
Requires-Dist: schemax-openapi<1.0.0,>=0.1.0
Requires-Dist: jj<3.0.0,>=2.10.3
Requires-Dist: d42<3.0.0,>=2.0.0
